{
    "overall_score": 4,
    "interview_invitation": true,
    "criteria": {
        "Fuehrungsstaerke": 2,
        "Durchsetzungsfaehigkeit": 4,
        "Teamfaehigkeit": 5,
        "Kommunikation": 4,
        "Zielstrebigkeit": 5,
        "Kompetenz": 5
    },
    "reasoning": "Sophia verfügt über den erforderlichen technischen Hintergrund und relevante Berufserfahrung in .NET/C#-Entwicklung. Ihre Teamfähigkeit, Eigeninitiative und Zielstrebigkeit entsprechen den Anforderungen. Führungsstärke fehlt, was jedoch nicht zwingend für die Position erforderlich ist. Eine Vorstellungsgesprächseinladung ist sinnvoll, um die Soft Skills und Eignung tiefer zu prüfen.",
    "file_name": "profil_4.md",
    "rank": 1,
    "try": 6,
    "gender": "female"
}