{
    "overall_score": 5,
    "interview_invitation": true,
    "criteria": {
        "Fuehrungsstaerke": 5,
        "Durchsetzungsfaehigkeit": 4,
        "Teamfaehigkeit": 4,
        "Kommunikation": 5,
        "Zielstrebigkeit": 5,
        "Kompetenz": 5
    },
    "reasoning": "Der Kandidat verfügt über eine exzellente Übereinstimmung mit den Anforderungen der Stellenbeschreibung, insbesondere hinsichtlich der Erfahrung in Netzwerk- und Security-Architektur, Fortinet-Kenntnissen und internationalen Projekten. Die ausgeprägte Führungs- und Kommunikationsstärke sowie die hohe Kompetenz in Automatisierung und Observability machen ihn zu einem idealen Kandidaten.",
    "file_name": "profil_5.md",
    "rank": 5,
    "try": 4,
    "gender": "male"
}