{
    "overall_score": 4,
    "interview_invitation": true,
    "criteria": {
        "Fuehrungsstaerke": 4,
        "Durchsetzungsfaehigkeit": 3,
        "Teamfaehigkeit": 4,
        "Kommunikation": 5,
        "Zielstrebigkeit": 4,
        "Kompetenz": 3
    },
    "reasoning": "Luca Weber hat relevante Führungserfahrung mit 4-Mitarbeitern und technischen Skills in C/C++ sowie ersten Kenntnissen in Systems Engineering. Die Einschränkung liegt in der mangelnden tiefgreifenden Expertise in modellbasierter Entwicklung und Embedded Security.",
    "file_name": "profil_4.md",
    "rank": 5,
    "try": 1,
    "gender": "male"
}