{
    "overall_score": 2,
    "interview_invitation": false,
    "criteria": {
        "Fuehrungsstaerke": 1,
        "Durchsetzungsfaehigkeit": 2,
        "Teamfaehigkeit": 3,
        "Kommunikation": 3,
        "Zielstrebigkeit": 2,
        "Kompetenz": 2
    },
    "reasoning": "Der Kandidat weist zwar grundlegende Kenntnisse im Netzwerkbetrieb auf, verfügt jedoch nicht über die erforderliche Erfahrung in der Architektur und Konzeption von Netzwerksicherheitslösungen. Zudem fehlen ihm Führungs- und PreSales-Erfahrung sowie fortgeschrittene Kenntnisse in relevanten Technologien wie SD-WAN, Cloud Networking und Network Automation. Die Sprachkenntnisse entsprechen nicht den Anforderungen.",
    "file_name": "profil_1.md",
    "rank": 4,
    "try": 4,
    "gender": "male"
}