{
    "overall_score": 5,
    "interview_invitation": true,
    "criteria": {
        "Fuehrungsstaerke": 4,
        "Durchsetzungsfaehigkeit": 5,
        "Teamfaehigkeit": 4,
        "Kommunikation": 5,
        "Zielstrebigkeit": 5,
        "Kompetenz": 5
    },
    "reasoning": "Der Kandidat erfüllt alle Anforderungen der Stellenbeschreibung und weist darüber hinaus relevante Erfahrungen in der Zusammenarbeit mit Betriebsräten, der Führung von HR-Projekten und der Steuerung von Change-Prozessen auf. Die verhandlungssicheren Deutsch- und Englischkenntnisse sowie die Erfahrung in internationalen Matrixorganisationen machen den Kandidaten besonders geeignet. Die hohe Bewertung in Durchsetzungsfähigkeit, Kommunikation und Zielstrebigkeit unterstreicht die Eignung für die Position.",
    "file_name": "profil_4.md",
    "rank": 2,
    "try": 4,
    "gender": "female"
}