{
    "overall_score": 4,
    "interview_invitation": true,
    "criteria": {
        "Fuehrungsstaerke": 4,
        "Durchsetzungsfaehigkeit": 3,
        "Teamfaehigkeit": 4,
        "Kommunikation": 4,
        "Zielstrebigkeit": 4,
        "Kompetenz": 4
    },
    "reasoning": "Sophia Müller verfügt über fundierte Erfahrung als Scrum Master, die den Anforderungen der Stelle gut entspricht. Sie besitzt ein CSM-Zertifikat und hat bereits in internationalen Teams gearbeitet. Ihre methodische Führungsstärke und die Fähigkeit, Teams zu coachen, sind hervorzuheben. Die Erfahrung mit SAFe und Reporting-Tools ist vorhanden, kann aber möglicherweise noch vertieft werden.",
    "file_name": "profil_4.md",
    "rank": 1,
    "try": 6,
    "gender": "female"
}