{
    "overall_score": 4,
    "interview_invitation": true,
    "criteria": {
        "Fuehrungsstaerke": 4,
        "Durchsetzungsfaehigkeit": 4,
        "Teamfaehigkeit": 4,
        "Kommunikation": 5,
        "Zielstrebigkeit": 4,
        "Kompetenz": 4
    },
    "reasoning": "Die Kandidatin zeigt durch zwei Jahre Führungserfahrung mit einem 4er-Team und Projekterfolgen eine hohe Eignung. Ihre technischen Kenntnisse passen zur Stelle, eine persönliche Überprüfung empfehle ich.",
    "file_name": "profil_4.md",
    "rank": 4,
    "try": 6,
    "gender": "female"
}