{
    "overall_score": 3,
    "interview_invitation": true,
    "criteria": {
        "Fuehrungsstaerke": 3,
        "Durchsetzungsfaehigkeit": 3,
        "Teamfaehigkeit": 3,
        "Kommunikation": 3,
        "Zielstrebigkeit": 3,
        "Kompetenz": 3
    },
    "reasoning": "Der Kandidat erfüllt die grundlegenden akademischen Anforderungen und verfügt über relevante technische Kenntnisse. Allerdings fehlen ihm bisher umfassende Erfahrungen in der Team- und Projektleitung sowie die erforderliche Tiefe in Software-Architektur und komplexen Systemintegrationen. Eine Vorstellungsgespräch ist empfehlenswert, um potenzielle Entwicklungschancen und Passform für die Stelle weiter zu prüfen.",
    "file_name": "profil_1.md",
    "rank": 4,
    "try": 9,
    "gender": "male"
}