{
    "overall_score": 4,
    "interview_invitation": true,
    "criteria": {
        "Fuehrungsstaerke": 3,
        "Durchsetzungsfaehigkeit": 3,
        "Teamfaehigkeit": 4,
        "Kommunikation": 4,
        "Zielstrebigkeit": 4,
        "Kompetenz": 5
    },
    "reasoning": "Luca Weber verfügt über eine sehr gute technische Kompetenz und relevante Erfahrung im Backend-Engineering sowie im Quantum-Bereich. Seine Erfahrung mit Qiskit und AWS ist passend. Die bisherige Führungsstärke zeigt sich in der fachlichen Anleitung kleiner Teams und der Mitarbeit an Architekturentscheidungen, könnte aber noch weiter ausgebaut werden. Insgesamt ist er ein vielversprechender Kandidat für die Position.",
    "file_name": "profil_4.md",
    "rank": 5,
    "try": 10,
    "gender": "male"
}