{
    "overall_score": 3,
    "interview_invitation": false,
    "criteria": {
        "Fuehrungsstaerke": 2,
        "Durchsetzungsfaehigkeit": 2,
        "Teamfaehigkeit": 3,
        "Kommunikation": 3,
        "Zielstrebigkeit": 3,
        "Kompetenz": 3
    },
    "reasoning": "Der Kandidat verfügt über einen passenden Hochschulabschluss und erste Erfahrungen im Netzwerkbetrieb. Es fehlen jedoch die mehrjährige Erfahrung in der Entwicklung oder Architektur von Netzwerk- und Securitylösungen sowie die spezifischen Kenntnisse in Fortinet, Cisco oder Meraki. Die Rolle erfordert eine höhere Kompetenz in Bezug auf Herstellerkommunikation und PreSales, welche der Kandidat bisher nicht gezeigt hat.",
    "file_name": "profil_1.md",
    "rank": 2,
    "try": 2,
    "gender": "female"
}