{
    "overall_score": 5,
    "interview_invitation": true,
    "criteria": {
        "Fuehrungsstaerke": 4,
        "Durchsetzungsfaehigkeit": 4,
        "Teamfaehigkeit": 5,
        "Kommunikation": 5,
        "Zielstrebigkeit": 5,
        "Kompetenz": 5
    },
    "reasoning": "Noah Müller verfügt über eine sehr hohe Eignung für die Position. Er besitzt umfassende Erfahrung als Scrum Master, insbesondere in internationalen Umgebungen mit KI-Programmen. Seine Zertifizierungen (PSM II, SAFe Scrum Master) und die nachweisbare Wirkung in komplexen Projekten unterstreichen seine Kompetenz. Die Erfahrung in der Moderation von Scrum-Events, der Beseitigung von Hindernissen und der teamübergreifenden Koordination passen ideal zu den Anforderungen.",
    "file_name": "profil_5.md",
    "rank": 1,
    "try": 2,
    "gender": "male"
}