{
    "overall_score": 5,
    "interview_invitation": true,
    "criteria": {
        "Fuehrungsstaerke": 4,
        "Durchsetzungsfaehigkeit": 3,
        "Teamfaehigkeit": 4,
        "Kommunikation": 5,
        "Zielstrebigkeit": 4,
        "Kompetenz": 5
    },
    "reasoning": "Die Kandidatin hat eine solide fachliche Expertise in Netzwerk- und Security-Architekturen mit ersten Führungserfahrungen, zeigt Kommunikationsstärke und technisches Engagement. Eine Einladung zu einem Gespräch empfehlenswert, um die Führungskompetenz weiter zu vertiefen.",
    "file_name": "profil_3.md",
    "rank": 1,
    "try": 4,
    "gender": "female"
}