{
    "overall_score": 4,
    "interview_invitation": true,
    "criteria": {
        "Fuehrungsstaerke": 4,
        "Durchsetzungsfaehigkeit": 3,
        "Teamfaehigkeit": 4,
        "Kommunikation": 4,
        "Zielstrebigkeit": 4,
        "Kompetenz": 4
    },
    "reasoning": "Hannah Weber hat relevante Scrum Master-Erfahrung mit Fokus auf Prozesse und Teamleitung. Ihre agilen Kenntnisse und Tools sind passend. Allerdings fehlt tiefer internationale Erfahrung und höhere Englisch-Kenntnisse.",
    "file_name": "profil_3.md",
    "rank": 5,
    "try": 3,
    "gender": "female"
}