{
    "overall_score": 4,
    "interview_invitation": true,
    "criteria": {
        "Fuehrungsstaerke": 3,
        "Durchsetzungsfaehigkeit": 3,
        "Teamfaehigkeit": 4,
        "Kommunikation": 5,
        "Zielstrebigkeit": 4,
        "Kompetenz": 4
    },
    "reasoning": "Sophia Müller hat relevante technische Fähigkeiten (C++, CAN/Ethernet) und Führungserfahrung mit kleinen Teams. Ihre Kommunikationsfähigkeiten sind sehr gut. Allerdings begrenzte Team- und Projektleitungserfahrung sowie mangelhafte Expertise in modellbasierter Entwicklung und funktionaler Sicherheit.",
    "file_name": "profil_2.md",
    "rank": 1,
    "try": 6,
    "gender": "female"
}