{
    "overall_score": 4,
    "interview_invitation": true,
    "criteria": {
        "Fuehrungsstaerke": 4,
        "Durchsetzungsfaehigkeit": 4,
        "Teamfaehigkeit": 5,
        "Kommunikation": 5,
        "Zielstrebigkeit": 4,
        "Kompetenz": 5
    },
    "reasoning": "Der Kandidat erfüllt die meisten Anforderungen sehr gut, insbesondere die fachliche Expertise und operative Erfahrung. Die fehlende disziplinarische Führungserfahrung und das begrenzte Englisch (B2) stellen leichte Einschränkungen dar, die jedoch durch weitere Gespräche überprüft werden können.",
    "file_name": "profil_3.md",
    "rank": 1,
    "try": 4,
    "gender": "male"
}