{
    "overall_score": 3,
    "interview_invitation": true,
    "criteria": {
        "Fuehrungsstaerke": 2,
        "Durchsetzungsfaehigkeit": 2,
        "Teamfaehigkeit": 4,
        "Kommunikation": 3,
        "Zielstrebigkeit": 3,
        "Kompetenz": 3
    },
    "reasoning": "Luca Weber zeigt grundlegende Kenntnisse im Scrum-Prozess und in der Moderation von Scrum-Events. Die Erfahrung als Junior Scrum Master ist jedoch begrenzt auf ein Jahr und ohne disziplinarische Führungsverantwortung. Die geplanten Zertifizierungen und die Bereitschaft zur Weiterentwicklung sind positiv. Die Sprachkenntnisse (Englisch B1) könnten für eine internationale Umgebung eine Herausforderung darstellen.",
    "file_name": "profil_2.md",
    "rank": 5,
    "try": 3,
    "gender": "male"
}