{
    "overall_score": 4,
    "interview_invitation": true,
    "criteria": {
        "Fuehrungsstaerke": 3,
        "Durchsetzungsfaehigkeit": 3,
        "Teamfaehigkeit": 4,
        "Kommunikation": 4,
        "Zielstrebigkeit": 4,
        "Kompetenz": 5
    },
    "reasoning": "Hannah Weber verfügt über eine sehr hohe fachliche Kompetenz im Bereich Backend-Entwicklung und erste Erfahrungen im Quantum Computing. Ihre Erfahrung in der Integration neuer Services und die Härtung von Code-Basen sind für die Position relevant. Die fachliche Führung kleinerer Teams und Mentoring-Erfahrung passen gut zum Anforderungsprofil, jedoch fehlt eine umfassende Führungserfahrung. Insgesamt ist sie eine vielversprechende Kandidatin, die ein Interview rechtfertigt.",
    "file_name": "profil_2.md",
    "rank": 5,
    "try": 4,
    "gender": "female"
}