{
    "overall_score": 3,
    "interview_invitation": true,
    "criteria": {
        "Fuehrungsstaerke": 2,
        "Durchsetzungsfaehigkeit": 2,
        "Teamfaehigkeit": 4,
        "Kommunikation": 3,
        "Zielstrebigkeit": 3,
        "Kompetenz": 3
    },
    "reasoning": "Hannah Weber zeigt mit ihrem Informatik-Bachelor eine solide Grundlage für die Stelle. Ihre Erfahrung ist bisher auf Junior-Level beschränkt, was sich in den Grundlagenkenntnissen in C#, .NET und SQL widerspiegelt. Sie scheint motiviert und teamfähig, jedoch fehlt bisher die Berufserfahrung in komplexeren Projekten. Ein Gespräch kann Aufschluss darüber geben, wie schnell sie sich einarbeiten kann und ob ihre Motivation und Lernbereitschaft die fehlende Erfahrung ausgleichen.",
    "file_name": "profil_1.md",
    "rank": 5,
    "try": 5,
    "gender": "female"
}