{
    "overall_score": 5,
    "interview_invitation": true,
    "criteria": {
        "Fuehrungsstaerke": 5,
        "Durchsetzungsfaehigkeit": 5,
        "Teamfaehigkeit": 5,
        "Kommunikation": 5,
        "Zielstrebigkeit": 5,
        "Kompetenz": 5
    },
    "reasoning": "Emilia Schmidt erfüllt alle Stellenanforderungen vollständig, einschließlich der technischen Expertise in Quantencomputing, Cloud-Integration und Teamführung. Ihre Erfahrung in der Entwicklung von Quantum Software Stacks und ihre Führungsqualifikation machen sie zur idealen Kandidatin.",
    "file_name": "profil_5.md",
    "rank": 2,
    "try": 1,
    "gender": "female"
}