{
    "overall_score": 5,
    "interview_invitation": true,
    "criteria": {
        "Fuehrungsstaerke": 4,
        "Durchsetzungsfaehigkeit": 4,
        "Teamfaehigkeit": 5,
        "Kommunikation": 4,
        "Zielstrebigkeit": 4,
        "Kompetenz": 5
    },
    "reasoning": "Der Kandidat verfügt über relevante technische Kompetenz und erste Führungserfahrung, die die Eignung für die Position als Lead Quantum Software Engineer nachweislich untermauern.",
    "file_name": "profil_1.md",
    "rank": 2,
    "try": 4,
    "gender": "male"
}