{
    "overall_score": 5,
    "interview_invitation": true,
    "criteria": {
        "Fuehrungsstaerke": 4,
        "Durchsetzungsfaehigkeit": 4,
        "Teamfaehigkeit": 4,
        "Kommunikation": 5,
        "Zielstrebigkeit": 5,
        "Kompetenz": 5
    },
    "reasoning": "Der Kandidat verfügt über umfangreiche Erfahrung in den in der Stellenbeschreibung geforderten Bereichen und bringt eine hohe technische Expertise mit. Die nachgewiesene Führungserfahrung in Projekten sowie die Kommunikationsstärke und Umsetzungsorientierung passen hervorragend zum Anforderungsprofil. Die Fortinet-Kenntnisse sind ein deutliches Plus.",
    "file_name": "profil_4.md",
    "rank": 3,
    "try": 3,
    "gender": "male"
}