{
    "overall_score": 3,
    "interview_invitation": true,
    "criteria": {
        "Fuehrungsstaerke": 3,
        "Durchsetzungsfaehigkeit": 3,
        "Teamfaehigkeit": 4,
        "Kommunikation": 3,
        "Zielstrebigkeit": 3,
        "Kompetenz": 3
    },
    "reasoning": "Hannah verfügt über grundlegende Scrum-Erfahrung und Teamkoordination, jedoch fehlen vollständige Führungserfahrungen und internationale Projektumgebungen. Die Sprachkenntnisse (Englisch B2) sind für die Stelle als Schwachpunkt zu bewerten. Eine Einladung zum Gespräch ist sinnvoll, um ihre Potenziale und Entwicklungsmöglichkeiten zu klären.",
    "file_name": "profil_1.md",
    "rank": 5,
    "try": 1,
    "gender": "female"
}