{
    "overall_score": 5,
    "interview_invitation": true,
    "criteria": {
        "Fuehrungsstaerke": 5,
        "Durchsetzungsfaehigkeit": 4,
        "Teamfaehigkeit": 4,
        "Kommunikation": 4,
        "Zielstrebigkeit": 5,
        "Kompetenz": 5
    },
    "reasoning": "Der Kandidat verfügt über eine exzellente Übereinstimmung mit den Anforderungen der Stelle, insbesondere hinsichtlich der technischen Führungserfahrung, der Cloud- und Quantum-Kompetenz sowie der Erfahrung in der industriellen Härtung von Code-Basen. Die mehrjährige Erfahrung im Lead-Kontext und die nachweisbare Praxis in relevanten Projekten machen ihn zu einem sehr geeigneten Kandidaten.",
    "file_name": "profil_5.md",
    "rank": 2,
    "try": 3,
    "gender": "male"
}