{
    "overall_score": 2,
    "interview_invitation": false,
    "criteria": {
        "Fuehrungsstaerke": 1,
        "Durchsetzungsfaehigkeit": 2,
        "Teamfaehigkeit": 3,
        "Kommunikation": 3,
        "Zielstrebigkeit": 3,
        "Kompetenz": 2
    },
    "reasoning": "Der Kandidat verfügt über einen passenden Hochschulabschluss und Grundkenntnisse im Client-Umfeld, jedoch fehlen umfassende Erfahrungen in Produktsteuerung, Budgetverantwortung und Führung. Die bisherige Tätigkeit im operativen Support deckt nicht die Anforderungen des Product Owner-Rolle ab.",
    "file_name": "profil_1.md",
    "rank": 1,
    "try": 1,
    "gender": "female"
}