{
    "overall_score": 5,
    "interview_invitation": true,
    "criteria": {
        "Fuehrungsstaerke": 5,
        "Durchsetzungsfaehigkeit": 5,
        "Teamfaehigkeit": 4,
        "Kommunikation": 5,
        "Zielstrebigkeit": 5,
        "Kompetenz": 5
    },
    "reasoning": "Noah Müller zeigte hervorragende Fähigkeiten in Führungsstärke, Durchsetzungsfähigkeit und Kompetenz, insbesondere durch Teamleitung, Mentoring und Expertise in relevanten Technologien wie Qiskit und AWS. Seine Erfahrung passt nahezu perfekt zur Stellenbeschreibung.",
    "file_name": "profil_2.md",
    "rank": 1,
    "try": 4,
    "gender": "male"
}