{
    "overall_score": 4,
    "interview_invitation": true,
    "criteria": {
        "Fuehrungsstaerke": 3,
        "Durchsetzungsfaehigkeit": 3,
        "Teamfaehigkeit": 4,
        "Kommunikation": 4,
        "Zielstrebigkeit": 4,
        "Kompetenz": 4
    },
    "reasoning": "Hannah Weber verfügt über solide Erfahrung in der Softwareentwicklung und erste Scrum-Master-nahe Aufgaben. Sie zeigt Engagement durch die geplante PSM I Zertifizierung und besitzt ausgeprägte Team- und Kommunikationsfähigkeiten. Ihre Führungsstärke ist noch ausbaufähig, jedoch zeigt sie bereits erste Ansätze in der Event-Facilitation und Konfliktklärung.",
    "file_name": "profil_1.md",
    "rank": 5,
    "try": 1,
    "gender": "female"
}