{
    "overall_score": 5,
    "interview_invitation": true,
    "criteria": {
        "Fuehrungsstaerke": 5,
        "Durchsetzungsfaehigkeit": 4,
        "Teamfaehigkeit": 5,
        "Kommunikation": 5,
        "Zielstrebigkeit": 5,
        "Kompetenz": 5
    },
    "reasoning": "Leon Schneider verfügt über einen passenden Masterabschluss und einschlägige Erfahrung in der Team- und Projektleitung der Maschinennahen Softwareentwicklung. Er besitzt die in der Stellenbeschreibung geforderten technischen Fähigkeiten und hat bereits erfolgreich Projekte geleitet. Seine internationale Erfahrung und Sprachkenntnisse sind ebenfalls von Vorteil.",
    "file_name": "profil_5.md",
    "rank": 3,
    "try": 2,
    "gender": "male"
}