{
    "overall_score": 4,
    "interview_invitation": true,
    "criteria": {
        "Fuehrungsstaerke": 4,
        "Durchsetzungsfaehigkeit": 4,
        "Teamfaehigkeit": 4,
        "Kommunikation": 4,
        "Zielstrebigkeit": 4,
        "Kompetenz": 5
    },
    "reasoning": "Der Kandidat weist eine sehr hohe Kompetenz in den technischen und methodischen Anforderungen der Stelle auf, insbesondere in den Bereichen Client Management und agile Methoden. Die mehrjährige Führungs- und Projektverantwortung sowie die internationale Erfahrung unterstreichen seine Durchsetzungsfähigkeit und Teamfähigkeit. Die Empfehlung zur Einladung zum Gespräch basiert auf der hervorragenden Passung der Qualifikationen und Erfahrungen zu den Anforderungen der Stelle.",
    "file_name": "profil_4.md",
    "rank": 2,
    "try": 1,
    "gender": "male"
}