{
    "overall_score": 5,
    "interview_invitation": true,
    "criteria": {
        "Fuehrungsstaerke": 5,
        "Durchsetzungsfaehigkeit": 5,
        "Teamfaehigkeit": 5,
        "Kommunikation": 5,
        "Zielstrebigkeit": 5,
        "Kompetenz": 5
    },
    "reasoning": "Kandidatin erfüllt alle Anforderungen der Stelle durch relevante Erfahrung, hervorragende Führungsergebnisse und fundierte technische Kompetenzen.",
    "file_name": "profil_4.md",
    "rank": 4,
    "try": 5,
    "gender": "female"
}