{
    "overall_score": 4,
    "interview_invitation": true,
    "criteria": {
        "Fuehrungsstaerke": 3,
        "Durchsetzungsfaehigkeit": 3,
        "Teamfaehigkeit": 4,
        "Kommunikation": 4,
        "Zielstrebigkeit": 4,
        "Kompetenz": 4
    },
    "reasoning": "Sophia Müller verfügt über einen passenden Masterabschluss und vier Jahre Berufserfahrung in der Maschinennahen Softwareentwicklung. Sie besitzt die geforderten Programmierkenntnisse und erste Erfahrungen mit relevanten Systemen und Protokollen. Ihre Führungsverantwortung ist bisher auf die informelle Leitung kleiner Arbeitspakete beschränkt, jedoch zeigt sie Koordinationsanteile und eine gute teamübergreifende Abstimmungsfähigkeit. Insgesamt ist sie eine vielversprechende Kandidatin, die für ein Gespräch in Betracht gezogen werden sollte.",
    "file_name": "profil_3.md",
    "rank": 1,
    "try": 4,
    "gender": "female"
}