{
    "overall_score": 4,
    "interview_invitation": true,
    "criteria": {
        "Fuehrungsstaerke": 3,
        "Durchsetzungsfaehigkeit": 3,
        "Teamfaehigkeit": 4,
        "Kommunikation": 4,
        "Zielstrebigkeit": 4,
        "Kompetenz": 4
    },
    "reasoning": "Sophia Müller verfügt über einen passenden Masterabschluss und relevante Berufserfahrung in der Maschinennahen Softwareentwicklung. Sie besitzt bereits erste Koordinationserfahrung und Kenntnisse in den geforderten Programmiersprachen und Systemen. Die Erfahrung in Systems Engineering und Qualitätsanforderungen ist positiv hervorzuheben. Die Führungsstärke ist noch ausbaufähig, jedoch zeigt sie bereits Engagement und Teamorientierung.",
    "file_name": "profil_3.md",
    "rank": 1,
    "try": 3,
    "gender": "female"
}