{
    "overall_score": 4,
    "interview_invitation": true,
    "criteria": {
        "Fuehrungsstaerke": 4,
        "Durchsetzungsfaehigkeit": 4,
        "Teamfaehigkeit": 4,
        "Kommunikation": 4,
        "Zielstrebigkeit": 4,
        "Kompetenz": 3
    },
    "reasoning": "Luca Weber hat relevante Fähigkeiten und Führungserfahrung, insbesondere im Mentoring und der technischen Anleitung. Allerdings fehlt eine tiefgreifende Expertise in der industriellen Härtung von Forschungscode sowie umfangreichere Führungserfahrung für ein komplexes Team.",
    "file_name": "profil_4.md",
    "rank": 5,
    "try": 9,
    "gender": "male"
}