{
    "overall_score": 5,
    "interview_invitation": true,
    "criteria": {
        "Fuehrungsstaerke": 5,
        "Durchsetzungsfaehigkeit": 4,
        "Teamfaehigkeit": 4,
        "Kommunikation": 5,
        "Zielstrebigkeit": 5,
        "Kompetenz": 5
    },
    "reasoning": "Der Kandidat verfügt über einen Masterabschluss in Informatik und mehrjährige Erfahrung als Lead IT Project Manager. Er besitzt exzellente Methodenkompetenz, starke Führungsverantwortung und umfassende technische Kenntnisse in Hard- und Softwareentwicklung. Seine Erfahrung in der Steuerung komplexer Projekte und die hohe Kommunikationsfähigkeit machen ihn zu einem idealen Kandidaten.",
    "file_name": "profil_5.md",
    "rank": 4,
    "try": 1,
    "gender": "male"
}