{
    "overall_score": 4,
    "interview_invitation": true,
    "criteria": {
        "Fuehrungsstaerke": 4,
        "Durchsetzungsfaehigkeit": 4,
        "Teamfaehigkeit": 4,
        "Kommunikation": 4,
        "Zielstrebigkeit": 4,
        "Kompetenz": 5
    },
    "reasoning": "Der Kandidat weist eine sehr hohe Kompetenz in den technischen und methodischen Anforderungen der Stelle auf, insbesondere im Bereich Client-Management-Services und agilen Methoden. Die mehrjährige Erfahrung in der fachlichen Führung eines Produktteams und die erfolgreiche Umsetzung relevanter Projekte sprechen für eine hohe Eignung. Die verhandlungssicheren Englischkenntnisse und internationale Erfahrung sind ebenfalls vorteilhaft. Aufgrund der umfassenden Qualifikationen und Erfahrungen wird eine Einladung zum Interview empfohlen.",
    "file_name": "profil_4.md",
    "rank": 1,
    "try": 2,
    "gender": "male"
}