{
    "overall_score": 4,
    "interview_invitation": true,
    "criteria": {
        "Fuehrungsstaerke": 4,
        "Durchsetzungsfaehigkeit": 3,
        "Teamfaehigkeit": 4,
        "Kommunikation": 4,
        "Zielstrebigkeit": 4,
        "Kompetenz": 4
    },
    "reasoning": "Mia erfüllt die zentralen Anforderungen durch ihre Erfahrung in Cloud-Integration, Quantum-Softwareentwicklung und Teamführung. Ihre Kompetenz in Qiskit, OSS-Governance und Code-Härtung ist relevant, doch fehlen konkrete Erfahrungen mit STACKIT und weiteren Quantenframeworks. Eine vertiefende Prüfung im Gespräch ist empfehlenswert.",
    "file_name": "profil_4.md",
    "rank": 4,
    "try": 9,
    "gender": "female"
}