{
    "overall_score": 4,
    "interview_invitation": true,
    "criteria": {
        "Fuehrungsstaerke": 4,
        "Durchsetzungsfaehigkeit": 3,
        "Teamfaehigkeit": 4,
        "Kommunikation": 4,
        "Zielstrebigkeit": 4,
        "Kompetenz": 4
    },
    "reasoning": "Emilia hat relevante Führungs- und technische Erfahrungen, die die Anforderungen teilweise erfüllen. Eine persönliche Überprüfung würde die Tiefe der Kompetenzen und die Teamführungspraxis genauer analysieren.",
    "file_name": "profil_4.md",
    "rank": 2,
    "try": 10,
    "gender": "female"
}