{
    "overall_score": 4,
    "interview_invitation": true,
    "criteria": {
        "Fuehrungsstaerke": 2,
        "Durchsetzungsfaehigkeit": 3,
        "Teamfaehigkeit": 4,
        "Kommunikation": 3,
        "Zielstrebigkeit": 4,
        "Kompetenz": 5
    },
    "reasoning": "Der Kandidat erfüllt die technischen Anforderungen vollständig und bringt relevante Erfahrung im .NET-Umfeld mit. Seine Teamfähigkeit und Zielstrebigkeit sind gut, jedoch fehlen Führungserfahrung und explizite Kommunikationskompetenzen. Eine Vorstellungsgesprächsinvitation ist sinnvoll, um Softskills und Eignung für die Kultur der Kufer Software GmbH zu prüfen.",
    "file_name": "profil_3.md",
    "rank": 1,
    "try": 2,
    "gender": "male"
}