{
    "overall_score": 5,
    "interview_invitation": true,
    "criteria": {
        "Fuehrungsstaerke": 4,
        "Durchsetzungsfaehigkeit": 4,
        "Teamfaehigkeit": 5,
        "Kommunikation": 5,
        "Zielstrebigkeit": 5,
        "Kompetenz": 5
    },
    "reasoning": "Emma Schneider verfügt über umfangreiche Erfahrung als Scrum Master in internationalen Umgebungen und zeigt starke Führungskompetenz sowie Teamfähigkeit. Ihre Fähigkeiten in der agilen Prozesssteuerung und ihr tiefes Verständnis von Scrum und SAFe machen sie zu einer hervorragenden Kandidatin. Ihre nachgewiesene Wirkung in komplexen Umgebungen und ihre ausgeprägten Kommunikationsfähigkeiten unterstreichen ihre Eignung für die Position.",
    "file_name": "profil_5.md",
    "rank": 3,
    "try": 4,
    "gender": "female"
}