{
    "overall_score": 3,
    "interview_invitation": true,
    "criteria": {
        "Fuehrungsstaerke": 3,
        "Durchsetzungsfaehigkeit": 4,
        "Teamfaehigkeit": 4,
        "Kommunikation": 4,
        "Zielstrebigkeit": 4,
        "Kompetenz": 3
    },
    "reasoning": "Die Kandidatin verfügt über relevante technische Grundkenntnisse und erste Führungserfahrung, zeigt aber noch ausreichendes Potenzial für die komplexe Rolle eines Product Owners.",
    "file_name": "profil_2.md",
    "rank": 4,
    "try": 3,
    "gender": "female"
}