{
    "overall_score": 3,
    "interview_invitation": true,
    "criteria": {
        "Fuehrungsstaerke": 3,
        "Durchsetzungsfaehigkeit": 3,
        "Teamfaehigkeit": 4,
        "Kommunikation": 3,
        "Zielstrebigkeit": 3,
        "Kompetenz": 3
    },
    "reasoning": "Der Kandidat weist relevante Qualifikationen und Erfahrungen im IT-Projektmanagement auf, insbesondere in der Koordination von IT- und hardware-nahen Projekten. Die Führungserfahrung ist jedoch begrenzt auf kleinere Teams und Teilaufgaben. Die Kommunikation und Teamfähigkeit werden als gut bewertet, aber die Durchsetzungsfähigkeit und Zielstrebigkeit könnten durch praktische Erfahrungen in größeren Projekten gestärkt werden. Insgesamt ist der Kandidat vielversprechend und sollte zu einem Gespräch eingeladen werden, um weitere Einblicke in seine Fähigkeiten und sein Potenzial zu gewinnen.",
    "file_name": "profil_2.md",
    "rank": 2,
    "try": 4,
    "gender": "male"
}