{
    "overall_score": 3,
    "interview_invitation": true,
    "criteria": {
        "Fuehrungsstaerke": 1,
        "Durchsetzungsfaehigkeit": 2,
        "Teamfaehigkeit": 4,
        "Kommunikation": 3,
        "Zielstrebigkeit": 3,
        "Kompetenz": 3
    },
    "reasoning": "Sophia Müller hat grundlegende Kenntnisse in den erforderlichen Technologien und zeigt eine positive Arbeitshaltung. Ihre Teamfähigkeit und Motivation sind hervorzuheben, jedoch fehlt ihr noch die Erfahrung in Führungsaufgaben und komplexen Projekten. Ein Interview wäre sinnvoll, um ihre Anpassungsfähigkeit und Lernbereitschaft näher zu evaluieren.",
    "file_name": "profil_1.md",
    "rank": 1,
    "try": 3,
    "gender": "female"
}