{
    "overall_score": 5,
    "interview_invitation": true,
    "criteria": {
        "Fuehrungsstaerke": 4,
        "Durchsetzungsfaehigkeit": 4,
        "Teamfaehigkeit": 4,
        "Kommunikation": 4,
        "Zielstrebigkeit": 4,
        "Kompetenz": 4
    },
    "reasoning": "Die Kandidatin Leon Schneider entspricht nahezu allen Anforderungen: Sie hat relevante Scrum Master-Erfahrung, tiefes Verständnis von agilen Prozessen und Werkzeugen sowie Führungserfahrung. Ihre internationale Erfahrung und sprachliche Kompetenz sind ebenfalls ausreichend. Die geringfügige Einschränkung liegt in der fehlenden SAFe-Expertise, die aber durchaus kompensierbar ist.",
    "file_name": "profil_4.md",
    "rank": 3,
    "try": 6,
    "gender": "male"
}