{
    "overall_score": 3,
    "interview_invitation": false,
    "criteria": {
        "Fuehrungsstaerke": 2,
        "Durchsetzungsfaehigkeit": 2,
        "Teamfaehigkeit": 3,
        "Kommunikation": 3,
        "Zielstrebigkeit": 3,
        "Kompetenz": 3
    },
    "reasoning": "Der Kandidat verfügt über einen passenden Hochschulabschluss und erste Erfahrungen im Netzwerkbetrieb. Allerdings fehlen die geforderten mehrjährigen Erfahrungen in der Entwicklung oder Architektur von Netzwerk- und Securitylösungen sowie die Expertise in Fortinet, Cisco und Meraki. Die bisherige Rolle war operativer Natur ohne Führungsverantwortung oder PreSales-Erfahrung.",
    "file_name": "profil_1.md",
    "rank": 1,
    "try": 4,
    "gender": "male"
}