{
    "overall_score": 5,
    "interview_invitation": true,
    "criteria": {
        "Fuehrungsstaerke": 5,
        "Durchsetzungsfaehigkeit": 5,
        "Teamfaehigkeit": 4,
        "Kommunikation": 5,
        "Zielstrebigkeit": 5,
        "Kompetenz": 5
    },
    "reasoning": "Der Kandidat erfüllt die Qualifikationsanforderungen vollständig, besitzt relevante Erfahrung in der operativen Personalarbeit sowie in der Verhandlungsführung mit Betriebsräten und hat strategische HR-Projekte erfolgreich geleitet. Seine technischen Kenntnisse und internationale Erfahrung entsprechen der Stellenbeschreibung.",
    "file_name": "profil_4.md",
    "rank": 5,
    "try": 2,
    "gender": "female"
}