{
    "overall_score": 4,
    "interview_invitation": true,
    "criteria": {
        "Fuehrungsstaerke": 3,
        "Durchsetzungsfaehigkeit": 4,
        "Teamfaehigkeit": 5,
        "Kommunikation": 5,
        "Zielstrebigkeit": 4,
        "Kompetenz": 4
    },
    "reasoning": "Die Kandidatin zeigt durch ihre moderаторische Rolle und Teamkoordination eine ausreichende Eignung. Ihre Erfahrung mit Scrum-Events und Jira sowie die geplante Zertifizierung unterstreichen die Kompetenz. Eine Einladung zu einem Gespräch empfehlenswert.",
    "file_name": "profil_1.md",
    "rank": 4,
    "try": 4,
    "gender": "male"
}