{
    "overall_score": 4,
    "interview_invitation": true,
    "criteria": {
        "Fuehrungsstaerke": 4,
        "Durchsetzungsfaehigkeit": 3,
        "Teamfaehigkeit": 5,
        "Kommunikation": 4,
        "Zielstrebigkeit": 4,
        "Kompetenz": 4
    },
    "reasoning": "Matteo Schmidt verfügt über fundierte Erfahrung als Scrum Master und bringt die notwendigen Kompetenzen für die Stelle mit. Seine mehrjährige Erfahrung, die CSM-Zertifizierung und die praktische Anwendung von Jira sowie agilen Metriken sind positiv hervorzuheben. Die internationale Erfahrung und gute Englischkenntnisse sind ebenfalls von Vorteil. Die Führungsstärke zeigt sich in der methodischen Teamführung, die Durchsetzungsfähigkeit ist anhand der gegebenen Informationen schwerer einzuschätzen.",
    "file_name": "profil_4.md",
    "rank": 2,
    "try": 5,
    "gender": "male"
}