{
    "overall_score": 4,
    "interview_invitation": true,
    "criteria": {
        "Fuehrungsstaerke": 3,
        "Durchsetzungsfaehigkeit": 3,
        "Teamfaehigkeit": 4,
        "Kommunikation": 4,
        "Zielstrebigkeit": 4,
        "Kompetenz": 4
    },
    "reasoning": "Emma Schneider verfügt über eine solide Basis als Scrum Master mit zwei Jahren Erfahrung und kennt sich mit den gängigen Tools und Prozessen aus. Ihre Erfahrung in der agilen Begleitung eines Teams und die Beteiligung an Programmzeremonien passen gut zur Stellenbeschreibung. Die Zertifizierung in Vorbereitung und die Bereitschaft zur kontinuierlichen Verbesserung unterstreichen ihre Zielstrebigkeit. Internationale Erfahrung ist bisher begrenzt, sollte aber keine unüberwindbare Hürde darstellen.",
    "file_name": "profil_3.md",
    "rank": 3,
    "try": 1,
    "gender": "female"
}