{
    "overall_score": 2,
    "interview_invitation": false,
    "criteria": {
        "Fuehrungsstaerke": 1,
        "Durchsetzungsfaehigkeit": 2,
        "Teamfaehigkeit": 3,
        "Kommunikation": 3,
        "Zielstrebigkeit": 2,
        "Kompetenz": 2
    },
    "reasoning": "Der Kandidat hat zwar eine relevante Ausbildung und einige Berufserfahrung im Netzwerkbetrieb, jedoch fehlen ihm die erforderlichen Fähigkeiten und Erfahrungen in der Architektur und Konzeption von Netzwerksicherheitslösungen, die für die Stelle des Senior Network & Security Solutions Architects notwendig sind. Zudem hat er keine Führungs- oder PreSales-Erfahrung, was für die Position ebenfalls relevant wäre. Die technischen Fähigkeiten sind nicht ausreichend für die gestellten Anforderungen.",
    "file_name": "profil_1.md",
    "rank": 5,
    "try": 3,
    "gender": "female"
}