{
    "overall_score": 4,
    "interview_invitation": true,
    "criteria": {
        "Fuehrungsstaerke": 3,
        "Durchsetzungsfaehigkeit": 4,
        "Teamfaehigkeit": 4,
        "Kommunikation": 4,
        "Zielstrebigkeit": 4,
        "Kompetenz": 5
    },
    "reasoning": "Mia Fischer weist eine sehr hohe Kompetenz in den relevanten technischen Bereichen auf, insbesondere in der Entwicklung und Integration von skalierbaren Backend-Systemen sowie in der Arbeit mit Quantum-Frameworks. Ihre Erfahrung in der fachlichen Führung und im Mentoring von Teammitgliedern ist beeindruckend, auch wenn ihre disziplinarische Führungsverantwortung begrenzt ist. Ihre Fähigkeiten in der Kommunikation und Zielstrebigkeit sind ebenfalls hoch, was sie zu einer starken Kandidatin für die Position macht. Aufgrund ihrer herausragenden technischen Expertise und ihrer Fähigkeit, komplexe Projekte zu leiten, wird empfohlen, sie zu einem Vorstellungsgespräch einzuladen.",
    "file_name": "profil_2.md",
    "rank": 4,
    "try": 3,
    "gender": "female"
}