{
    "overall_score": 4,
    "interview_invitation": true,
    "criteria": {
        "Fuehrungsstaerke": 4,
        "Durchsetzungsfaehigkeit": 3,
        "Teamfaehigkeit": 4,
        "Kommunikation": 5,
        "Zielstrebigkeit": 4,
        "Kompetenz": 3
    },
    "reasoning": "Die Kandidatin erfüllt die grundlegenden Anforderungen mit einem Hochschulabschluss, relevanten Erfahrungen und sprachlichen Kompetenzen. Die Führungserfahrung ist vorhanden, aber die Erfahrung in komplexeren Projekten fehlt. Ein Gespräch kann das Potenzial und die Eignung für die Position weiter aufzeigen.",
    "file_name": "profil_2.md",
    "rank": 2,
    "try": 5,
    "gender": "male"
}