{
    "overall_score": 4,
    "interview_invitation": true,
    "criteria": {
        "Fuehrungsstaerke": 3,
        "Durchsetzungsfaehigkeit": 3,
        "Teamfaehigkeit": 4,
        "Kommunikation": 4,
        "Zielstrebigkeit": 4,
        "Kompetenz": 4
    },
    "reasoning": "Der Kandidat verfügt über einen passenden Masterabschluss und relevante Berufserfahrung in der Softwareentwicklung, insbesondere mit C++. Erste Erfahrungen in der Koordination von Teilprojekten und die Mitarbeit an Anforderungs- und Planungsaufgaben sind positiv hervorzuheben. Die Basiskenntnisse in CAN, Ethernet und SPS sowie die Erfahrung mit funktionaler Sicherheit sind ebenfalls relevant. Die Führungsverantwortung ist bisher noch gering, jedoch vorhanden.",
    "file_name": "profil_2.md",
    "rank": 3,
    "try": 2,
    "gender": "male"
}