{
    "overall_score": 4,
    "interview_invitation": true,
    "criteria": {
        "Fuehrungsstaerke": 4,
        "Durchsetzungsfaehigkeit": 3,
        "Teamfaehigkeit": 4,
        "Kommunikation": 3,
        "Zielstrebigkeit": 3,
        "Kompetenz": 4
    },
    "reasoning": "Die Kandidatin zeigt durch die Führung eines moderaten Teams und die Verbesserung der Teamstruktur eine hohe Eignung. Mit der geplanten Scrum-Zertifizierung und praktischer Erfahrung im agilen Umfeld ist sie sehr gut geeignet.",
    "file_name": "profil_2.md",
    "rank": 1,
    "try": 3,
    "gender": "female"
}