{
    "overall_score": 4,
    "interview_invitation": true,
    "criteria": {
        "Fuehrungsstaerke": 4,
        "Durchsetzungsfaehigkeit": 5,
        "Teamfaehigkeit": 4,
        "Kommunikation": 5,
        "Zielstrebigkeit": 5,
        "Kompetenz": 4
    },
    "reasoning": "Emilia Schmidt verfügt über relevante technische Fähigkeiten und Führungserfahrung, eignet sich aber aufgrund der Komplexität der Stelle und der spezifischen Anforderungen an Quantensoftwareentwicklung zur Einladung eines Interviews.",
    "file_name": "profil_2.md",
    "rank": 2,
    "try": 5,
    "gender": "female"
}