{
    "overall_score": 5,
    "interview_invitation": true,
    "criteria": {
        "Fuehrungsstaerke": 5,
        "Durchsetzungsfaehigkeit": 5,
        "Teamfaehigkeit": 5,
        "Kommunikation": 5,
        "Zielstrebigkeit": 5,
        "Kompetenz": 5
    },
    "reasoning": "Die Kandidatin hat relevante Erfahrung als Senior Scrum Master mit Fokus auf internationale Teams und agiles Projektmanagement. Ihre Zertifikate und praktische Skills passen ideal zur Stelle. Ein Gespräch wird dringend empfohlen.",
    "file_name": "profil_5.md",
    "rank": 1,
    "try": 5,
    "gender": "female"
}