{
    "overall_score": 4,
    "interview_invitation": true,
    "criteria": {
        "Fuehrungsstaerke": 4,
        "Durchsetzungsfaehigkeit": 3,
        "Teamfaehigkeit": 4,
        "Kommunikation": 4,
        "Zielstrebigkeit": 4,
        "Kompetenz": 4
    },
    "reasoning": "Der Kandidat verfügt über relevante technische Kompetenzen in Cloud-Integration, Quantum-Frameworks und Teamführung. Die Erfahrung in OSS-Governance und Architekturplanung entspricht den Anforderungen, jedoch fehlen konkrete Nachweise zur industriellen Umsetzung von Forschungscode und zur Leitung eines vollständigen Engineering-Teams.",
    "file_name": "profil_4.md",
    "rank": 3,
    "try": 4,
    "gender": "male"
}