{
    "overall_score": 3,
    "interview_invitation": true,
    "criteria": {
        "Fuehrungsstaerke": 1,
        "Durchsetzungsfaehigkeit": 2,
        "Teamfaehigkeit": 4,
        "Kommunikation": 4,
        "Zielstrebigkeit": 4,
        "Kompetenz": 4
    },
    "reasoning": "Kandidatin erfüllt die technischen Anforderungen durch C#-Kenntnisse und SQL-Erfahrung. Mit ihrer Teamfähigkeit, Eigenständigkeit und hohen Lernbereitschaft zeigt sie Potenzial für die Position.",
    "file_name": "profil_3.md",
    "rank": 1,
    "try": 6,
    "gender": "male"
}