{
    "overall_score": 4,
    "interview_invitation": true,
    "criteria": {
        "Fuehrungsstaerke": 3,
        "Durchsetzungsfaehigkeit": 3,
        "Teamfaehigkeit": 4,
        "Kommunikation": 3,
        "Zielstrebigkeit": 4,
        "Kompetenz": 4
    },
    "reasoning": "Matteo verfügt über relevante technische Kompetenzen, einschließlich Qiskit-Erfahrung und Cloud-Integration. Seine Mentoring-Erfahrung und Projektverantwortung zeigen Zielstrebigkeit und Teamfähigkeit. Führungsstärke und Durchsetzungsfähigkeit erscheinen jedoch noch eingeschränkt, weshalb ein Gespräch zur Vertiefung erforderlich ist.",
    "file_name": "profil_3.md",
    "rank": 2,
    "try": 2,
    "gender": "male"
}