{
    "overall_score": 4,
    "interview_invitation": true,
    "criteria": {
        "Fuehrungsstaerke": 3,
        "Durchsetzungsfaehigkeit": 3,
        "Teamfaehigkeit": 4,
        "Kommunikation": 4,
        "Zielstrebigkeit": 4,
        "Kompetenz": 4
    },
    "reasoning": "Emma Schneider verfügt über einen passenden akademischen Hintergrund und mehrjährige Erfahrung in der Quantum-Entwicklung, ergänzt durch solide Backend-Kenntnisse. Ihre erste technische Anleitung von Teammitgliedern und die Mitarbeit an produktnahen Integrationen zeigen Potenzial für die Teamführung. Die Erfahrung im Umgang mit Open-Source-Code und die Fähigkeit, Forschungsergebnisse in industrielle Anwendungen zu überführen, sind besonders relevant.",
    "file_name": "profil_1.md",
    "rank": 3,
    "try": 3,
    "gender": "female"
}