{
    "overall_score": 4,
    "interview_invitation": true,
    "criteria": {
        "Fuehrungsstaerke": 3,
        "Durchsetzungsfaehigkeit": 3,
        "Teamfaehigkeit": 4,
        "Kommunikation": 3,
        "Zielstrebigkeit": 4,
        "Kompetenz": 4
    },
    "reasoning": "Luca Weber verfügt über relevante technische Kompetenzen und Erfahrung in Quantensoftwareentwicklung sowie Grundlagen in Cloud-Technologien. Seine Mentoring-Erfahrung und Zielstrebigkeit sind vorhanden, jedoch fehlen klare Belege für umfassende Führungsverantwortung und tiefgehende Cloud-Integrationserfahrung. Eine Einladung zum Gespräch zur Vertiefung der Führungs- und Cloud-Expertise ist empfehlenswert.",
    "file_name": "profil_1.md",
    "rank": 5,
    "try": 6,
    "gender": "male"
}