{
    "overall_score": 5,
    "interview_invitation": true,
    "criteria": {
        "Fuehrungsstaerke": 4,
        "Durchsetzungsfaehigkeit": 4,
        "Teamfaehigkeit": 4,
        "Kommunikation": 4,
        "Zielstrebigkeit": 4,
        "Kompetenz": 5
    },
    "reasoning": "Der Kandidat erfüllt alle technischen Anforderungen durch relevante Quantum-Erfahrung und Cloud-Kenntnisse. Die Führungserfahrung mit Teams bestätigt die Führungsqualifikation. Die Gesamtleistung und Impact-Orientierung der Projekte unterstreichen die hohe Eignung.",
    "file_name": "profil_5.md",
    "rank": 5,
    "try": 9,
    "gender": "male"
}