{
    "overall_score": 4,
    "interview_invitation": true,
    "criteria": {
        "Fuehrungsstaerke": 4,
        "Durchsetzungsfaehigkeit": 4,
        "Teamfaehigkeit": 4,
        "Kommunikation": 4,
        "Zielstrebigkeit": 4,
        "Kompetenz": 4
    },
    "reasoning": "Die Kandidatin erfüllt die erforderlichen Basisanforderungen mit relevantem Studium und Berufserfahrung. Ihre Führungserfahrung ist begrenzt, aber sie zeigt Potenzial. Die technischen Kenntnisse und agile Methoden sind vorhanden. Ein Gespräch würde die Kommunikationsfähigkeiten und die Führungsqualitäten näher beleuchten.",
    "file_name": "profil_3.md",
    "rank": 3,
    "try": 1,
    "gender": "female"
}