{
    "overall_score": 4,
    "interview_invitation": true,
    "criteria": {
        "Fuehrungsstaerke": 3,
        "Durchsetzungsfaehigkeit": 3,
        "Teamfaehigkeit": 4,
        "Kommunikation": 4,
        "Zielstrebigkeit": 4,
        "Kompetenz": 4
    },
    "reasoning": "Die Kandidatin verfügt über einen passenden Masterabschluss und 4 Jahre Berufserfahrung in der Maschinensoftwareentwicklung. Sie besitzt relevante Programmierkenntnisse und erste Erfahrungen in IEC 61131-3. Ihre Koordinationserfahrung und die Mitarbeit in Projekten zeigen Teamfähigkeit und Zielstrebigkeit. Die Führungsstärke ist noch ausbaufähig, jedoch bereits durch die informelle Leitung von Arbeitspaketen angedeutet.",
    "file_name": "profil_3.md",
    "rank": 4,
    "try": 2,
    "gender": "female"
}