{
    "overall_score": 3,
    "interview_invitation": true,
    "criteria": {
        "Fuehrungsstaerke": 2,
        "Durchsetzungsfaehigkeit": 3,
        "Teamfaehigkeit": 3,
        "Kommunikation": 3,
        "Zielstrebigkeit": 3,
        "Kompetenz": 3
    },
    "reasoning": "Der Kandidat verfügt über grundlegende Projektmanagementkenntnisse und eine relevante Ausbildung, jedoch fehlen Führungserfahrung und praktische Hardwareerfahrung. Die Kommunikationskenntnisse sind ausreichend, aber nicht auf einem hohen Niveau. Eine Vorstellungsgesprächsinvitation ist sinnvoll, um das Potenzial für Weiterbildung und die Eignung für die Stelle genauer zu prüfen.",
    "file_name": "profil_1.md",
    "rank": 1,
    "try": 5,
    "gender": "male"
}