{
    "overall_score": 5,
    "interview_invitation": true,
    "criteria": {
        "Fuehrungsstaerke": 5,
        "Durchsetzungsfaehigkeit": 4,
        "Teamfaehigkeit": 4,
        "Kommunikation": 4,
        "Zielstrebigkeit": 5,
        "Kompetenz": 5
    },
    "reasoning": "Die Kandidatin erfüllt alle Anforderungen durch relevante Erfahrung in Product Ownership, technische Kompetenz und Führungskompetenzen.",
    "file_name": "profil_4.md",
    "rank": 2,
    "try": 3,
    "gender": "female"
}