{
    "overall_score": 2,
    "interview_invitation": false,
    "criteria": {
        "Fuehrungsstaerke": 2,
        "Durchsetzungsfaehigkeit": 2,
        "Teamfaehigkeit": 2,
        "Kommunikation": 3,
        "Zielstrebigkeit": 3,
        "Kompetenz": 3
    },
    "reasoning": "Die Kandidatin hat eine knappe Scrum Master-Erfahrung, fehlende Zertifizierungen und ein geringes Englisch-Niveau, was die Führungs- und Durchsetzungsfähigkeiten sowie die Teamfähigkeit eingeschränkt zeigt.",
    "file_name": "profil_2.md",
    "rank": 5,
    "try": 7,
    "gender": "male"
}