{
    "overall_score": 3,
    "interview_invitation": true,
    "criteria": {
        "Fuehrungsstaerke": 3,
        "Durchsetzungsfaehigkeit": 3,
        "Teamfaehigkeit": 4,
        "Kommunikation": 4,
        "Zielstrebigkeit": 3,
        "Kompetenz": 3
    },
    "reasoning": "Kandidat hat relevante technische Kenntnisse und erste Führungs-Erfahrung, zeigt aber noch Entwicklungspotenzial bei komplexen Architekturaufgaben und umfassender Teamleitung.",
    "file_name": "profil_2.md",
    "rank": 5,
    "try": 1,
    "gender": "male"
}