{
    "overall_score": 4,
    "interview_invitation": true,
    "criteria": {
        "Fuehrungsstaerke": 3,
        "Durchsetzungsfaehigkeit": 4,
        "Teamfaehigkeit": 5,
        "Kommunikation": 5,
        "Zielstrebigkeit": 4,
        "Kompetenz": 4
    },
    "reasoning": "Kandidatin verfügt über relevante technische Kenntnisse (C/C++, IEC 61131-3) und erste Führungserfahrung. Die Führungserfahrung mit kleinen Teams zeigt Potenzial, aber die Stelle erfordert leitende Tätigkeit mit mehr als 3 Mitarbeitern. Die geringe Erfahrung in komplexen SW-Methoden und funktionaler Sicherheit könnte die Eignung beeinträchtigen.",
    "file_name": "profil_3.md",
    "rank": 5,
    "try": 1,
    "gender": "female"
}