{
    "overall_score": 3,
    "interview_invitation": true,
    "criteria": {
        "Fuehrungsstaerke": 3,
        "Durchsetzungsfaehigkeit": 3,
        "Teamfaehigkeit": 4,
        "Kommunikation": 3,
        "Zielstrebigkeit": 3,
        "Kompetenz": 3
    },
    "reasoning": "Der Kandidat hat solide technische Kenntnisse und erste Führungserfahrung, jedoch fehlt es an umfassender internationaler Projektverantwortung und Budgetverantwortung. Die Englischkenntnisse sind nicht verhandlungssicher, was für die internationale Rolle ein Hindernis sein könnte. Dennoch zeigt der Kandidat Potenzial und könnte für die Stelle geeignet sein, wenn weitere Qualifikationen in den genannten Bereichen vorhanden sind.",
    "file_name": "profil_2.md",
    "rank": 5,
    "try": 4,
    "gender": "male"
}