{
    "overall_score": 4,
    "interview_invitation": true,
    "criteria": {
        "Fuehrungsstaerke": 4,
        "Durchsetzungsfaehigkeit": 4,
        "Teamfaehigkeit": 5,
        "Kommunikation": 5,
        "Zielstrebigkeit": 5,
        "Kompetenz": 5
    },
    "reasoning": "Kandidatin zeigt relevante Skills und erste Führungserfahrung. Die Eignung ist hoch, doch die Führungspraxis mit 14 Mitarbeitenden sollte in einem Gespräch vertieft werden.",
    "file_name": "profil_3.md",
    "rank": 1,
    "try": 5,
    "gender": "male"
}