{
    "overall_score": 4,
    "interview_invitation": true,
    "criteria": {
        "Fuehrungsstaerke": 3,
        "Durchsetzungsfaehigkeit": 3,
        "Teamfaehigkeit": 4,
        "Kommunikation": 4,
        "Zielstrebigkeit": 4,
        "Kompetenz": 4
    },
    "reasoning": "Der Kandidat erfüllt die fachlichen Anforderungen und bringt relevante Erfahrungen in der Projektarbeit sowie Grundlagen in Hardware-/Softwareentwicklung mit. Die Führungserfahrung ist auf kleinerem Maßstab vorhanden, aber die Kompetenz und Zielstrebigkeit sprechen für eine Weiterführung im Gespräch.",
    "file_name": "profil_2.md",
    "rank": 3,
    "try": 2,
    "gender": "female"
}